{"bikes": [{"manufacturer_name": "Bianchi", "is_stock_img": false, "thumb": "https://files.bikeindex.org/uploads/Pu/8720/small_1342890467.jpg", "title": "2011 Bianchi Volpe", "large_img": "https://files.bikeindex.org/uploads/Pu/8720/large_1342890467.jpg", "stolen_location": "Oakland,CA,94618", "id": 25121, "stolen": true, "frame_colors": ["Brown"], "year": 2011, "frame_model": "Volpe", "serial": "CX0306450F", "date_stolen": 1342677600}, {"manufacturer_name": "Yeti", "is_stock_img": false, "thumb": "https://files.bikeindex.org/uploads/Pu/8461/small_1343081896.jpg", "title": "1996 Yeti AS3", "large_img": "https://files.bikeindex.org/uploads/Pu/8461/large_1343081896.jpg", "stolen_location": "San Francisco,CA,94103", "id": 24312, "stolen": true, "frame_colors": ["Yellow or Gold", "Red"], "year": 1996, "frame_model": "AS3", "serial": "absent", "date_stolen": 1342677600}, {"manufacturer_name": "Specialized", "is_stock_img": false, "thumb": null, "title": "2008 Specialized Hard Rock Comp Disc", "large_img": null, "stolen_location": "Benicia,CA,94510", "id": 25074, "stolen": true, "frame_colors": ["Black"], "year": 2008, "frame_model": "Hard Rock  Comp Disc", "serial": "P7LAI0548", "date_stolen": 1342504800}, {"manufacturer_name": "Trek", "is_stock_img": false, "thumb": "https://files.bikeindex.org/uploads/Pu/8967/small_1342483418.jpg", "title": "2012 Trek 7.2 FX", "large_img": "https://files.bikeindex.org/uploads/Pu/8967/large_1342483418.jpg", "stolen_location": "San Francisco,CA,94123", "id": 25873, "stolen": true, "frame_colors": ["Black"], "year": 2012, "frame_model": "7.2 FX", "serial": "WTF052c29576", "date_stolen": 1342332000}, {"manufacturer_name": "SCOTT", "is_stock_img": false, "thumb": null, "title": "2012 SCOTT CR1 Team", "large_img": null, "stolen_location": "Brisbane,CA,94005", "id": 24293, "stolen": true, "frame_colors": ["White", "Black"], "year": 2012, "frame_model": "CR1 Team", "serial": "STR08D25611033412", "date_stolen": 1342245600}, {"manufacturer_name": "Novara", "is_stock_img": false, "thumb": "https://files.bikeindex.org/uploads/Pu/9329/small_1342394746.jpg", "title": "2008 Novara Fusion", "large_img": "https://files.bikeindex.org/uploads/Pu/9329/large_1342394746.jpg", "stolen_location": "Oakland,CA,94607", "id": 26920, "stolen": true, "frame_colors": ["Green"], "year": 2008, "frame_model": "Fusion", "serial": "absent", "date_stolen": 1342159200}, {"manufacturer_name": "Electra", "is_stock_img": false, "thumb": null, "title": "2010 Electra Townie 8D", "large_img": null, "stolen_location": "Oakland,CA,94607", "id": 25867, "stolen": true, "frame_colors": ["Blue"], "year": 2010, "frame_model": "Townie 8D", "serial": "ELW0D08220", "date_stolen": 1342159200}, {"manufacturer_name": "Trek", "is_stock_img": false, "thumb": null, "title": "1991 Trek 790", "large_img": null, "stolen_location": "Oakland,CA,94612", "id": 34119, "stolen": true, "frame_colors": ["Blue"], "year": 1991, "frame_model": "790", "serial": "absent", "date_stolen": 1342159200}, {"manufacturer_name": "Torker", "is_stock_img": false, "thumb": "https://files.bikeindex.org/uploads/Pu/8966/small_1342395277.jpg", "title": "Torker Boardwalk", "large_img": "https://files.bikeindex.org/uploads/Pu/8966/large_1342395277.jpg", "stolen_location": "Oakland,CA,94607", "id": 25872, "stolen": true, "frame_colors": ["Blue", "White"], "year": null, "frame_model": "Boardwalk", "serial": "absent", "date_stolen": 1342159200}, {"manufacturer_name": "Marin Bikes", "is_stock_img": false, "thumb": null, "title": "2011 Marin Bikes Bear Valley", "large_img": null, "stolen_location": "San Francisco,CA,94111", "id": 25050, "stolen": true, "frame_colors": ["White"], "year": 2011, "frame_model": "Bear Valley", "serial": "CA11241HSC127", "date_stolen": 1342159200}, {"manufacturer_name": "Scattante", "is_stock_img": false, "thumb": null, "title": "2010 Scattante 330", "large_img": null, "stolen_location": "San Francisco,CA,94117", "id": 25025, "stolen": true, "frame_colors": ["Black"], "year": 2010, "frame_model": "330", "serial": "icfj10f01087", "date_stolen": 1342072800}, {"manufacturer_name": "Diamondback", "is_stock_img": false, "thumb": null, "title": "2010 Diamondback vital 3", "large_img": null, "stolen_location": "Foster City,CA,94404", "id": 24990, "stolen": true, "frame_colors": ["Green"], "year": 2010, "frame_model": "vital 3", "serial": "SGP09E008896", "date_stolen": 1341727200}, {"manufacturer_name": "Cannondale", "is_stock_img": false, "thumb": null, "title": "2011 Cannondale womens quick 4", "large_img": null, "stolen_location": "Alameda,CA,94501", "id": 25567, "stolen": true, "frame_colors": ["Silver or Gray"], "year": 2011, "frame_model": "womens quick 4", "serial": "mm02628", "date_stolen": 1341727200}, {"manufacturer_name": "Giant", "is_stock_img": false, "thumb": "https://files.bikeindex.org/uploads/Pu/8959/small_1341881935.jpg", "title": "2012 Giant Suede", "large_img": "https://files.bikeindex.org/uploads/Pu/8959/large_1341881935.jpg", "stolen_location": "S An Francisco,CA,94133", "id": 25849, "stolen": true, "frame_colors": ["Silver or Gray"], "year": 2012, "frame_model": "Suede", "serial": "C22s4810", "date_stolen": 1341554400}, {"manufacturer_name": "Giant", "is_stock_img": true, "thumb": "https://bikebook.s3.amazonaws.com/uploads/Fr/8839/small_Rainier_20copy.jpg", "title": "2006 Giant Rainier", "large_img": "https://bikebook.s3.amazonaws.com/uploads/Fr/8839/Rainier_20copy.jpg", "stolen_location": "San Francisco,CA,94122", "id": 25096, "stolen": true, "frame_colors": ["Silver or Gray"], "year": 2006, "frame_model": "Rainier", "serial": "GE679147", "date_stolen": 1341468000}, {"manufacturer_name": "Trek", "is_stock_img": false, "thumb": "https://files.bikeindex.org/uploads/Pu/2656/small_1385602666.jpg", "title": "2006 Trek 1200", "large_img": "https://files.bikeindex.org/uploads/Pu/2656/large_1385602666.jpg", "stolen_location": "San Francisco,CA,94122", "id": 5969, "stolen": true, "frame_colors": ["Black", "White"], "year": 2006, "frame_model": "1200", "serial": "C15BT090", "date_stolen": 1341381600}, {"manufacturer_name": "Masi", "is_stock_img": false, "thumb": null, "title": "2008 Masi speciale commuter", "large_img": null, "stolen_location": "Albany,CA,94706", "id": 15674, "stolen": true, "frame_colors": ["Orange"], "year": 2008, "frame_model": "speciale commuter", "serial": "c71207709", "date_stolen": 1341381600}, {"manufacturer_name": "Specialized", "is_stock_img": false, "thumb": "https://files.bikeindex.org/uploads/Pu/9019/small_1341525958.jpg", "title": "2010 Specialized Era", "large_img": "https://files.bikeindex.org/uploads/Pu/9019/large_1341525958.jpg", "stolen_location": "San Francisco,CA,94102", "id": 25995, "stolen": true, "frame_colors": ["White"], "year": 2010, "frame_model": "Era", "serial": "M9LK66716", "date_stolen": 1341381600}, {"manufacturer_name": "Raleigh", "is_stock_img": false, "thumb": null, "title": "1999 Raleigh M40", "large_img": null, "stolen_location": "San Francisco,CA,94131", "id": 25093, "stolen": true, "frame_colors": ["Silver or Gray"], "year": 1999, "frame_model": "M40", "serial": "absent", "date_stolen": 1341208800}, {"manufacturer_name": "Klein Bikes", "is_stock_img": false, "thumb": "https://files.bikeindex.org/uploads/Pu/8627/small_1341296903.jpg", "title": "2002 Klein Bikes Quantam Pro", "large_img": "https://files.bikeindex.org/uploads/Pu/8627/large_1341296903.jpg", "stolen_location": "San Francisco,CA,94105", "id": 24827, "stolen": true, "frame_colors": ["Red", "Orange", "Yellow or Gold"], "year": 2002, "frame_model": "Quantam Pro", "serial": "CH0007098", "date_stolen": 1341208800}, {"manufacturer_name": "Surly", "is_stock_img": false, "thumb": "https://files.bikeindex.org/uploads/Pu/8615/small_1341104987.jpg", "title": "2009 Surly 1X1", "large_img": "https://files.bikeindex.org/uploads/Pu/8615/large_1341104987.jpg", "stolen_location": "San Francisco,CA,94103", "id": 24798, "stolen": true, "frame_colors": ["Orange"], "year": 2009, "frame_model": "1X1", "serial": "absent", "date_stolen": 1341036000}, {"manufacturer_name": "Specialized", "is_stock_img": true, "thumb": "https://bikebook.s3.amazonaws.com/uploads/Fr/4191/small_6805", "title": "2011 Specialized Tarmac SL3 Pro Frameset", "large_img": "https://bikebook.s3.amazonaws.com/uploads/Fr/4191/6805", "stolen_location": "Burlingame,CA,94010", "id": 94697, "stolen": true, "frame_colors": ["Black"], "year": 2011, "frame_model": "Tarmac SL3 Pro Frameset", "serial": "STAV310X0283", "date_stolen": 1341036000}, {"manufacturer_name": "Trek", "is_stock_img": true, "thumb": "https://bikebook.s3.amazonaws.com/uploads/Fr/1507/small_21wsd_whiteblack.jpg", "title": "2009 Trek 2.1 WSD", "large_img": "https://bikebook.s3.amazonaws.com/uploads/Fr/1507/21wsd_whiteblack.jpg", "stolen_location": "Burlingame,CA,94010", "id": 94721, "stolen": true, "frame_colors": ["Orange"], "year": 2009, "frame_model": "2.1 WSD", "serial": "WTU037G0661D", "date_stolen": 1341036000}, {"manufacturer_name": "Schwinn", "is_stock_img": false, "thumb": null, "title": "Schwinn Voyager", "large_img": null, "stolen_location": "Corte Madera,CA,94925", "id": 24790, "stolen": true, "frame_colors": ["Green"], "year": null, "frame_model": "Voyager", "serial": "absent", "date_stolen": 1340949600}, {"manufacturer_name": "Nicaea", "is_stock_img": false, "thumb": null, "title": "2010 Nicaea", "large_img": null, "stolen_location": "San Francisco,CA,94123", "id": 24792, "stolen": true, "frame_colors": ["White"], "year": 2010, "frame_model": null, "serial": "absent", "date_stolen": 1340949600}]}