{"bikes": [{"thumb": "https://files.bikeindex.org/uploads/Pu/16570/small_20140906_173727.jpg", "serial": "H5A41718", "id": 34810, "stolen": true, "date_stolen": 1416204000, "title": "Bianchi Milano Dama", "stolen_location": "San Francisco,CA,94103", "frame_model": "Milano Dama", "year": null, "large_img": "https://files.bikeindex.org/uploads/Pu/16570/large_20140906_173727.jpg", "is_stock_img": false, "manufacturer_name": "Bianchi", "frame_colors": ["Black"]}, {"thumb": null, "serial": "DAU14C008388", "id": 34872, "stolen": true, "date_stolen": 1416204000, "title": "2014 Diamondback Insight", "stolen_location": "Oakland,CA,94618", "frame_model": "Insight", "year": 2014, "large_img": null, "is_stock_img": false, "manufacturer_name": "Diamondback", "frame_colors": ["Red"]}, {"thumb": "https://files.bikeindex.org/uploads/Pu/16647/small_trek1000.jpg", "serial": "absent", "id": 34914, "stolen": true, "date_stolen": 1416204000, "title": "Trek 1000SL", "stolen_location": "Berkeley,CA,94703", "frame_model": "1000SL", "year": null, "large_img": "https://files.bikeindex.org/uploads/Pu/16647/large_trek1000.jpg", "is_stock_img": false, "manufacturer_name": "Trek", "frame_colors": ["Orange", "Red"]}, {"thumb": null, "serial": "WTU113C6433H", "id": 34815, "stolen": true, "date_stolen": 1416204000, "title": "2013 Trek FX 7.2", "stolen_location": "Berkeley,CA,94705", "frame_model": "FX 7.2", "year": 2013, "large_img": null, "is_stock_img": false, "manufacturer_name": "Trek", "frame_colors": ["Black"]}, {"thumb": "https://files.bikeindex.org/uploads/Pu/16698/small_885226_561341387232327_37348189_o.jpg", "serial": "absent", "id": 34946, "stolen": true, "date_stolen": 1416204000, "title": "2012 Simplon Pavo", "stolen_location": "Berkeley,CA,94704", "frame_model": "Pavo", "year": 2012, "large_img": "https://files.bikeindex.org/uploads/Pu/16698/large_885226_561341387232327_37348189_o.jpg", "is_stock_img": false, "manufacturer_name": "Simplon", "frame_colors": ["White"]}, {"thumb": null, "serial": "absent", "id": 38604, "stolen": true, "date_stolen": 1416117600, "title": "Raleigh Raleigh", "stolen_location": "San Francisco,94110", "frame_model": "Raleigh", "year": null, "large_img": null, "is_stock_img": false, "manufacturer_name": "Raleigh", "frame_colors": ["Green"]}, {"thumb": null, "serial": "SBC601070251", "id": 34819, "stolen": true, "date_stolen": 1416117600, "title": "2013 Specialized Dolce Comp C2", "stolen_location": "San Francisco,CA,94114", "frame_model": "Dolce Comp C2", "year": 2013, "large_img": null, "is_stock_img": false, "manufacturer_name": "Specialized", "frame_colors": ["Black"]}, {"thumb": "https://files.bikeindex.org/uploads/Pu/16546/small_bike.jpg", "serial": "CYIDCO9K00359", "id": 34778, "stolen": true, "date_stolen": 1416117600, "title": "2013 Motobecane Motobecane Messenger_52cm Blue", "stolen_location": "Oakland,CA,94609", "frame_model": "Motobecane Messenger_52cm Blue", "year": 2013, "large_img": "https://files.bikeindex.org/uploads/Pu/16546/large_bike.jpg", "is_stock_img": false, "manufacturer_name": "Motobecane", "frame_colors": ["Blue"]}, {"thumb": "https://files.bikeindex.org/uploads/Pu/16527/small_IMG_0529.jpg", "serial": "008US70713656N56", "id": 34767, "stolen": true, "date_stolen": 1416117600, "title": "Motobecane Sprint", "stolen_location": "San Francisco,CA", "frame_model": "Sprint", "year": null, "large_img": "https://files.bikeindex.org/uploads/Pu/16527/large_IMG_0529.jpg", "is_stock_img": false, "manufacturer_name": "Motobecane", "frame_colors": ["Silver or Gray"]}, {"thumb": "https://files.bikeindex.org/uploads/Pu/16512/small_Screen_Shot_2014-11-15_at_6.05.56_PM.png", "serial": "absent", "id": 34749, "stolen": true, "date_stolen": 1416031200, "title": "Aegis corsaro", "stolen_location": "Berkeley,CA,94703", "frame_model": "corsaro ", "year": null, "large_img": "https://files.bikeindex.org/uploads/Pu/16512/large_Screen_Shot_2014-11-15_at_6.05.56_PM.png", "is_stock_img": false, "manufacturer_name": "Aegis", "frame_colors": ["Black", "Yellow or Gold"]}, {"thumb": null, "serial": "D6263M0 ICK28A0786", "id": 34742, "stolen": true, "date_stolen": 1416031200, "title": "2007 K2 Easystreet Deuce", "stolen_location": "San Francisco,CA,94103", "frame_model": "Easystreet Deuce", "year": 2007, "large_img": null, "is_stock_img": false, "manufacturer_name": "K2", "frame_colors": ["Silver or Gray"]}, {"thumb": "https://files.bikeindex.org/uploads/Pu/16526/small_my_surly.jpg", "serial": "M13124342", "id": 34765, "stolen": true, "date_stolen": 1416031200, "title": "2014 Surly Disc Trucker", "stolen_location": "San Francisco,CA,94111", "frame_model": "Disc Trucker", "year": 2014, "large_img": "https://files.bikeindex.org/uploads/Pu/16526/large_my_surly.jpg", "is_stock_img": false, "manufacturer_name": "Surly", "frame_colors": ["Red"]}, {"thumb": "https://files.bikeindex.org/uploads/Pu/16700/small_2014-10-24_09.12.03.jpg", "serial": "UO6K14872", "id": 34952, "stolen": true, "date_stolen": 1416031200, "title": "Avanti Giro 3.0", "stolen_location": "San Francisco,CA,94118", "frame_model": "Giro 3.0", "year": null, "large_img": "https://files.bikeindex.org/uploads/Pu/16700/large_2014-10-24_09.12.03.jpg", "is_stock_img": false, "manufacturer_name": "Avanti", "frame_colors": ["White"]}, {"thumb": "https://files.bikeindex.org/uploads/Pu/16561/small_IMG_20140317_091546.jpg", "serial": "013C0977J", "id": 34798, "stolen": true, "date_stolen": 1416031200, "title": "2014 Trek 7.3 FX", "stolen_location": "San Francisco,CA,94110", "frame_model": "7.3 FX", "year": 2014, "large_img": "https://files.bikeindex.org/uploads/Pu/16561/large_IMG_20140317_091546.jpg", "is_stock_img": false, "manufacturer_name": "Trek", "frame_colors": ["Black"]}, {"thumb": "https://files.bikeindex.org/uploads/Pu/16485/small_4300_black.jpg", "serial": "WTU189C0006D", "id": 34726, "stolen": true, "date_stolen": 1416031200, "title": "2009 Trek 4300", "stolen_location": "San Francisco,CA,94103", "frame_model": "4300", "year": 2009, "large_img": "https://files.bikeindex.org/uploads/Pu/16485/large_4300_black.jpg", "is_stock_img": false, "manufacturer_name": "Trek", "frame_colors": ["Black"]}, {"thumb": "https://files.bikeindex.org/uploads/Pu/16515/small_langster.jpg", "serial": "602042576I", "id": 34730, "stolen": true, "date_stolen": 1416031200, "title": "2014 Specialized LANGSTER STREET", "stolen_location": "San Francisco,CA,94110", "frame_model": "LANGSTER STREET", "year": 2014, "large_img": "https://files.bikeindex.org/uploads/Pu/16515/large_langster.jpg", "is_stock_img": false, "manufacturer_name": "Specialized", "frame_colors": ["Silver or Gray"]}, {"thumb": null, "serial": "absent", "id": 34908, "stolen": true, "date_stolen": 1416031200, "title": "1983 Panasonic Mountain Cat 3500", "stolen_location": "Oakland,CA,94608", "frame_model": "Mountain Cat 3500", "year": 1983, "large_img": null, "is_stock_img": false, "manufacturer_name": "Panasonic", "frame_colors": ["Yellow or Gold"]}, {"thumb": null, "serial": "WUD111242", "id": 34770, "stolen": true, "date_stolen": 1415944800, "title": "2004 Specialized Large", "stolen_location": "San Francisco,CA,94122", "frame_model": "Large", "year": 2004, "large_img": null, "is_stock_img": false, "manufacturer_name": "Specialized", "frame_colors": ["White"]}, {"thumb": "https://files.bikeindex.org/uploads/Pu/16479/small_IMG_5829.jpg", "serial": "VOXK34490", "id": 34712, "stolen": true, "date_stolen": 1415944800, "title": "2011 Jamis Ventura Race Femme", "stolen_location": "San Francisco,CA,94110", "frame_model": "Ventura Race Femme", "year": 2011, "large_img": "https://files.bikeindex.org/uploads/Pu/16479/large_IMG_5829.jpg", "is_stock_img": false, "manufacturer_name": "Jamis", "frame_colors": ["White", "Blue"]}, {"thumb": "https://files.bikeindex.org/uploads/Pu/16424/small_IMG_0455.jpg", "serial": "absent", "id": 34688, "stolen": true, "date_stolen": 1415944800, "title": "2009 Specialized 10 Sirrus Sport", "stolen_location": "San Francisco,CA,94110", "frame_model": "10 Sirrus Sport", "year": 2009, "large_img": "https://files.bikeindex.org/uploads/Pu/16424/large_IMG_0455.jpg", "is_stock_img": false, "manufacturer_name": "Specialized", "frame_colors": ["Blue"]}, {"thumb": null, "serial": "absent", "id": 34704, "stolen": true, "date_stolen": 1415858400, "title": "Yazoo Freebike F.5", "stolen_location": "Berkeley,CA,94704", "frame_model": "Freebike F.5", "year": null, "large_img": null, "is_stock_img": false, "manufacturer_name": "Yazoo", "frame_colors": ["Blue"]}, {"thumb": "https://files.bikeindex.org/uploads/Pu/16379/small_IMG_0037.JPG", "serial": "wtu240g0180e", "id": 34660, "stolen": true, "date_stolen": 1415858400, "title": "2010 Gary Fisher Ion Pro GS", "stolen_location": "San Francisco,CA", "frame_model": "Ion Pro GS", "year": 2010, "large_img": "https://files.bikeindex.org/uploads/Pu/16379/large_IMG_0037.JPG", "is_stock_img": false, "manufacturer_name": "Gary Fisher", "frame_colors": ["White"]}, {"thumb": "https://files.bikeindex.org/uploads/Pu/16460/small_District_bike.jpg", "serial": "WTU330C1879E", "id": 34706, "stolen": true, "date_stolen": 1415858400, "title": "2011 Trek District", "stolen_location": "San Francisco,CA,94103", "frame_model": "District", "year": 2011, "large_img": "https://files.bikeindex.org/uploads/Pu/16460/large_District_bike.jpg", "is_stock_img": false, "manufacturer_name": "Trek", "frame_colors": ["Green"]}, {"thumb": "https://files.bikeindex.org/uploads/Pu/16484/small_Schwinn_Searcher4.jpg", "serial": "SSNIDC13L00465", "id": 34725, "stolen": true, "date_stolen": 1415858400, "title": "2014 Schwinn Searcher 4 Womens", "stolen_location": "San Anselmo,CA,94960", "frame_model": "Searcher 4 Womens", "year": 2014, "large_img": "https://files.bikeindex.org/uploads/Pu/16484/large_Schwinn_Searcher4.jpg", "is_stock_img": false, "manufacturer_name": "Schwinn", "frame_colors": ["Silver or Gray"]}, {"thumb": "https://files.bikeindex.org/uploads/Pu/16270/small_Advantix-016.JPG", "serial": "absent", "id": 34609, "stolen": true, "date_stolen": 1415685600, "title": "Giant Rainier", "stolen_location": "San Francisco,CA,94110", "frame_model": "Rainier", "year": null, "large_img": "https://files.bikeindex.org/uploads/Pu/16270/large_Advantix-016.JPG", "is_stock_img": false, "manufacturer_name": "Giant", "frame_colors": ["Silver or Gray", "Black"]}]}